armord
